[
  {
    "date": "2026-04-16",
    "currency": "AED",
    "rate": 129.07
  },
  {
    "date": "2026-04-16",
    "currency": "AMD",
    "rate": 12.78
  },
  {
    "date": "2026-04-16",
    "currency": "AUD",
    "rate": 338.35
  },
  {
    "date": "2026-04-16",
    "currency": "AZN",
    "rate": 279.69
  },
  {
    "date": "2026-04-16",
    "currency": "BRL",
    "rate": 95.12
  },
  {
    "date": "2026-04-16",
    "currency": "BYN",
    "rate": 166.67
  },
  {
    "date": "2026-04-16",
    "currency": "CAD",
    "rate": 344.06
  },
  {
    "date": "2026-04-16",
    "currency": "CHF",
    "rate": 605.93
  },
  {
    "date": "2026-04-16",
    "currency": "CNY",
    "rate": 69.5
  },
  {
    "date": "2026-04-16",
    "currency": "CZK",
    "rate": 22.93
  },
  {
    "date": "2026-04-16",
    "currency": "DKK",
    "rate": 74.72
  },
  {
    "date": "2026-04-16",
    "currency": "EUR",
    "rate": 558.28
  },
  {
    "date": "2026-04-16",
    "currency": "GBP",
    "rate": 642.14
  },
  {
    "date": "2026-04-16",
    "currency": "GEL",
    "rate": 178.36
  },
  {
    "date": "2026-04-16",
    "currency": "HKD",
    "rate": 60.51
  },
  {
    "date": "2026-04-16",
    "currency": "HUF",
    "rate": 15.33
  },
  {
    "date": "2026-04-16",
    "currency": "INR",
    "rate": 5.07
  },
  {
    "date": "2026-04-16",
    "currency": "IRR",
    "rate": 0.4
  },
  {
    "date": "2026-04-16",
    "currency": "JPY",
    "rate": 2.98
  },
  {
    "date": "2026-04-16",
    "currency": "KGS",
    "rate": 5.42
  },
  {
    "date": "2026-04-16",
    "currency": "KRW",
    "rate": 32.1
  },
  {
    "date": "2026-04-16",
    "currency": "KWD",
    "rate": 1547.76
  },
  {
    "date": "2026-04-16",
    "currency": "MDL",
    "rate": 28.05
  },
  {
    "date": "2026-04-16",
    "currency": "MXN",
    "rate": 27.4
  },
  {
    "date": "2026-04-16",
    "currency": "MYR",
    "rate": 120.02
  },
  {
    "date": "2026-04-16",
    "currency": "NOK",
    "rate": 50.27
  },
  {
    "date": "2026-04-16",
    "currency": "PLN",
    "rate": 131.67
  },
  {
    "date": "2026-04-16",
    "currency": "RUB",
    "rate": 6.26
  },
  {
    "date": "2026-04-16",
    "currency": "SAR",
    "rate": 126.37
  },
  {
    "date": "2026-04-16",
    "currency": "SEK",
    "rate": 51.51
  },
  {
    "date": "2026-04-16",
    "currency": "SGD",
    "rate": 372.7
  },
  {
    "date": "2026-04-16",
    "currency": "THB",
    "rate": 14.78
  },
  {
    "date": "2026-04-16",
    "currency": "TJS",
    "rate": 50.43
  },
  {
    "date": "2026-04-16",
    "currency": "TRY",
    "rate": 10.59
  },
  {
    "date": "2026-04-16",
    "currency": "UAH",
    "rate": 10.89
  },
  {
    "date": "2026-04-16",
    "currency": "USD",
    "rate": 474.08
  },
  {
    "date": "2026-04-16",
    "currency": "UZS",
    "rate": 3.89
  },
  {
    "date": "2026-04-16",
    "currency": "XDR",
    "rate": 651.78
  },
  {
    "date": "2026-04-16",
    "currency": "ZAR",
    "rate": 28.93
  }
]